MANIFEST.in
README.md
pyproject.toml
setup.py
amuse_halogen.egg-info/PKG-INFO
amuse_halogen.egg-info/SOURCES.txt
amuse_halogen.egg-info/dependency_links.txt
amuse_halogen.egg-info/requires.txt
amuse_halogen.egg-info/top_level.txt
src/amuse/community/halogen/Makefile
src/amuse/community/halogen/__init__.py
src/amuse/community/halogen/_version.py
src/amuse/community/halogen/interface.cc
src/amuse/community/halogen/interface.h
src/amuse/community/halogen/interface.py
src/amuse/community/halogen/src/Makefile
src/amuse/community/halogen/src/definitions.h
src/amuse/community/halogen/src/drand48.c
src/amuse/community/halogen/src/functions.c
src/amuse/community/halogen/src/functions.h
src/amuse/community/halogen/src/halogen4muse.c
src/amuse/community/halogen/src/routines.c
src/amuse/community/halogen/src/routines.h
src/amuse/community/halogen/src/doc/HALOGEN4MUSE.pdf
src/amuse/community/halogen/src/doc/HALOGEN4MUSE.tex
support/__init__.py
support/classifiers.py
support/config.py
support/generate_main.py
support/getsp.class
support/getsp.java
support/misc.py
support/setup_codes.py
support/version.py